Metadata-Version: 2.1
Name: odoo-addon-account_payment_term_partner_holiday
Version: 16.0.1.0.1
Summary: Account Payment Term Partner Holiday
Home-page: https://github.com/OCA/account-payment
Author: Tecnativa, Odoo Community Association (OCA)
Author-email: support@odoo-community.org
License: AGPL-3
Classifier: Programming Language :: Python
Classifier: Framework :: Odoo
Classifier: Framework :: Odoo :: 16.0
Classifier: License :: OSI Approved :: GNU Affero General Public License v3
Classifier: Development Status :: 4 - Beta
Requires-Python: >=3.10
Requires-Dist: odoo-addon-account-payment-term-extension<16.1dev,>=16.0dev
Requires-Dist: odoo<16.1dev,>=16.0a
